blogin/__init__.py
blogin-1.1.dist-info/LICENSE
blogin-1.1.dist-info/METADATA
blogin-1.1.dist-info/WHEEL
blogin-1.1.dist-info/entry_points.txt
blogin-1.1.dist-info/top_level.txt
blogin-1.1.dist-info/RECORD
