Metadata-Version: 2.1
Name: blogin
Version: 1.1
Summary: Login
Home-page: https://github.com/BotolMehedi/bdroid
Author: BotolMehedi
Author-email: Botol@email.com
License: UNKNOWN
Platform: UNKNOWN
Classifier: Programming Language :: Python :: 2
Classifier: License :: OSI Approved :: MIT License
Classifier: Operating System :: OS Independent
Requires-Python: >=2.7
